MANIFEST.in
setup.py
src/pypi_rankings/__init__.py
src/pypi_rankings/__version__.py
src/pypi_rankings/webserver.py
src/pypi_rankings.egg-info/PKG-INFO
src/pypi_rankings.egg-info/SOURCES.txt
src/pypi_rankings.egg-info/dependency_links.txt
src/pypi_rankings.egg-info/entry_points.txt
src/pypi_rankings.egg-info/namespace_packages.txt
src/pypi_rankings.egg-info/not-zip-safe
src/pypi_rankings.egg-info/requires.txt
src/pypi_rankings.egg-info/top_level.txt
src/pypi_rankings/crawlers/__init__.py
src/pypi_rankings/crawlers/bitbucket.py
src/pypi_rankings/crawlers/dependencies.py
src/pypi_rankings/crawlers/github.py
src/pypi_rankings/crawlers/progress.py
src/pypi_rankings/crawlers/pypi.py
src/pypi_rankings/crawlers/setup_executor.py
src/pypi_rankings/static/jquery.blockUI-custom-settings.js
src/pypi_rankings/static/jquery.blockUI.js
src/pypi_rankings/static/jquery.dataTables.min.js
src/pypi_rankings/static/jquery.js
src/pypi_rankings/static/logo.png
src/pypi_rankings/static/main.css
src/pypi_rankings/static/python_logo.png
src/pypi_rankings/static/solarized.css
src/pypi_rankings/static/spin.min.js
src/pypi_rankings/static/spinner.factory.js
src/pypi_rankings/templates/author.html
src/pypi_rankings/templates/index.html
src/pypi_rankings/templates/more_stats.html
src/pypi_rankings/templates/package.html