Metadata-Version: 1.1
Name: pypi-rankings
Version: 0.1.post5
Summary: show PyPI rankings
Home-page: https://github.com/wiggin15/pypi_rankings
Author: Arnon Yaari
Author-email: arnony@infinidat.com
License: PSF
Platform: UNKNOWN
Classifier: Intended Audience :: Developers
Classifier: Intended Audience :: System Administrators
Classifier: License :: OSI Approved :: Python Software Foundation License
Classifier: Operating System :: OS Independent
Classifier: Programming Language :: Python
Classifier: Topic :: Software Development :: Libraries :: Python Modules
